phyloki/__init__.py
phyloki/dataset4itol.py
phyloki/fetch_metadata.py
phyloki/get_hosts.py
phyloki/get_hosts_order.py
phyloki/get_organisms.py
phyloki/get_seqs.py
phyloki/phyloki.py
phyloki/read_accession_file.py
phyloki/update_tree.py
phyloki/version.py
phyloki-0.5.52.dist-info/LICENSE
phyloki-0.5.52.dist-info/METADATA
phyloki-0.5.52.dist-info/WHEEL
phyloki-0.5.52.dist-info/entry_points.txt
phyloki-0.5.52.dist-info/top_level.txt
phyloki-0.5.52.dist-info/RECORD
