Metadata-Version: 2.2
Name: phyloki
Version: 0.5.52
Summary: Annotate phylogenetic trees like never before
Home-page: https://github.com/iliapopov17/phyloki
Author: Ilia Popov
Author-email: iljapopov17@gmail.com
Requires-Python: >=3.10
License-File: LICENSE
Requires-Dist: biopython==1.85
Requires-Dist: numpy==2.2.0
Requires-Dist: pandas==2.2.3
Dynamic: author
Dynamic: author-email
Dynamic: description
Dynamic: description-content-type
Dynamic: home-page
Dynamic: requires-dist
Dynamic: requires-python
Dynamic: summary
